{"/5TxP6rB5Xsj6wML99MSww==":"logo2.png","JUpgpVa9M3eE8hz7fUwEuQ==":"man-4.jpg","Cj73YKUSweiqZWIyBQIMyA==":"man-3.jpg","3mFfXUT1y8B3fwSyXYr0aQ==":"office-3.jpg","/91eTlLhSrxpEuJFfPl5JA==":"people-1.jpg","GQe5UKKpjNqvU2Iueeuj7g==":"people-5.jpg","h8KY1su/OIw9c4FGAVRMfg==":"people-4.jpg","DW3izTzZPnAwHlq6YXV1iQ==":"team1.jpg","BYkFurULi1/d9Pm0xGeZkw==":"team4.jpg","b+buQZikE+5p3sfc8xp+eg==":"team3.jpg","FdhK5xex5lG+IFoSKix1zA==":"team2.jpg","Ds0ZPi5MrRROJS7+E30MTw==":"people-7.jpg","De0xWFfobXC0T2fGD50qeg==":"people-8.jpg","5AK8fv4dCu80nLED2koZ9Q==":"people-2.jpg","Iibf37HbcPcrIjAyvqeXRg==":"electric.jpg","GwgqTOFN3vX9VO+GWRzG7w==":"woody.jpg","1jX64VR+DXf0UtYHzUmkuw==":"sneakers.jpg","L36dmC5RsIPDlRS7z9wNCg==":"bike.jpg","qb71uR5rI2P+sE0WiHyXNg==":"interion.jpg","MgAG9EkFmX1dCRR0VK3baA==":"website1-736x736.jpg","uDZiyle+9tvvLsE9fvUZYA==":"webdevelopment-736x736.jpg","YRWa8mjABmPXrcX9YTeTIQ==":"marketing-736x736.jpg","Z1OmxAdQQ/W7mKFnySmEKg==":"website2-736x736.jpg","rUgtcpsred9qKiA0MH+Gug==":"pikaso_texttoimage_people-working-in-a-marketing-agency-with-green-tu%20(1)-1216x832.jpg","QyaSvqOh9xUqy6Qga9iO/A==":"mbr-965x1448.jpg","fL/LdsOPVH/yN52kz5JfPA==":"designer%20(36)-759x759.jpg","iB5MO55YO5Oxw9l2lTqeJw==":"designer%20(34)-759x759.jpg","HoeblEwaN0Xx4aj0jQPz4g==":"designer%20(47)-759x759.jpg","ncc3785Hv8XlU2dLFyDhTA==":"logo%20camale%C3%A3o%20verde%20cofortaa-121x121.png","epYeodhFaVUthvyjGUP6xg==":"mbr-965x1448.jpeg","1lU2YRRDmIzh4B8hDmOvmA==":"mbr-1-965x1448.jpeg","PNe4ydSk8rFgwTvjzkI1TQ==":"logo%20camale%C3%A3o%20verde%20cofortaa-972x972.png","eB+FdTIlNf4Q3bLuW9ozRg==":"logo%20camale%C3%A3o%20verde%20cofortaa-1080x1080.jpg","/hLAqc3d7Uri5uTQ8hUkyw==":"bg-3.jpg","S9CjzSWnFHCPpiqq0h3SdA==":"bg-1.jpg","td+TuAm6gzMVJIYDfOd7PQ==":"background1.jpg","jawZvnkJMfKvFsScSRgXbA==":"background1-1.jpg","dTNBW7o4gu/cHpql1IC1iw==":"mbr-2-965x1448.jpeg","oUOA34H6pSc1oAPmVn1LBg==":"background3.jpg"}